{"Which": 0, "of": 1, "the": 2, "following": 3, "is": 4, "responsible": 5, "for": 6, "cyan": 7, "cube": 8, "moves": 9, "up": 10, "a": 11, "bit?": 12, "QEND": 13, "gray": 14, "cylinder": 15, "hit": 16, "END": 17, "blue": 18, "was": 19, "pushed": 20, "away?": 21, "yellow": 22, "came": 23, "from": 24, "left": 25, "bumped": 26, "into": 27, "cylinder?": 28, "collides": 29, "with": 30, "purple": 31, "upwards?": 32, "green": 33, "ball": 34, "ball?": 35, "moved": 36, "cube?": 37, "side": 38, "collided": 39, "silver": 40, "red": 41, "right": 42, "above": 43, "brown": 44, "southeast": 45, "collided?": 46, "away": 47, "moved?": 48, "bumps": 49, "east": 50, "changes": 51, "direction?": 52, "tagged": 53, "comes": 54, "to": 55, "right?": 56, "goes": 57, "east?": 58, "towards": 59, "bounced": 60, "off": 61, "go": 62, "forward": 63, "pushes": 64, "by": 65, "sideswipes": 66, "slows": 67, "down?": 68, "sphere": 69, "down": 70, "sideswiped": 71, "gold": 72, "travels": 73, "in": 74, "bottom": 75, "left?": 76, "path": 77, "north": 78, "west?": 79, "its": 80, "path?": 81, "screen": 82, "and": 83, "hits": 84, "below": 85, "downwards": 86, "spins?": 87, "direction": 88, "rubber": 89, "far": 90, "west": 91, "thrown": 92, "velocity": 93, "side?": 94, "middle": 95, "after": 96, "being": 97, "struck": 98, "begins": 99, "moving": 100, "northeast": 101, "stops": 102, "moving?": 103, "upwards": 104, "metallic": 105, "hit?": 106, "at": 107, "steady": 108, "had": 109, "been": 110, "dashed": 111, "forcefully": 112, "pathway?": 113, "moves?": 114, "already": 115, "downward": 116, "rolled": 117, "up?": 118, "rolls": 119, "stood": 120, "motionless": 121, "southwest": 122, "that": 123, "spins": 124, "out": 125, "scene": 126, "metal": 127, "stop": 128, "bit": 129, "shiny": 130, "velocity?": 131, "northeast?": 132, "changed": 133, "sphere's": 134, "colliding": 135, "events": 136, "objects": 137, "filter_material": 138, "filter_shape": 139, "unique": 140, "filter_collision": 141, "filter_ancestor": 142, "belong_to": 143, "What": 144, "will": 145, "happen": 146, "next?": 147, "unseen_events": 148, "without": 149, "all_events": 150, "filter_counterfact": 151, "not": 152, "cube's": 153, "exit?": 154, "filter_color": 155, "filter_out": 156, "negate": 157, "object's": 158, "sphere?": 159, "If": 160, "object": 161, "removed,": 162, "which": 163, "happen?": 164, "object?": 165, "cylinder's": 166, "event": 167, "collision": 168, "between": 169, "Without": 170, "cylinder,": 171, "if": 172, "removed?": 173, "exiting": 174, "scene?": 175, "what": 176, "object,": 177, "sphere,": 178, "cube,": 179}